hdmc/__init__.py
hdmc/__main__.py
hdmc/ll2_aod.py
hdmc/road.py
hdmc-0.2.dist-info/LICENSE
hdmc-0.2.dist-info/METADATA
hdmc-0.2.dist-info/WHEEL
hdmc-0.2.dist-info/top_level.txt
hdmc-0.2.dist-info/RECORD
