Metadata-Version: 2.1
Name: hdmc
Version: 0.2
Summary: HD map converter between Lanelet2 and Apollo OpenDRIVE
Home-page: UNKNOWN
Author: Slastnikova Anna
Author-email: slastnikova02@mail.ru
License: UNKNOWN
Keywords: converter,apollo,opendrive,oscar,lanelet2,hdmap
Platform: UNKNOWN
Classifier: Programming Language :: Python :: 3
Classifier: License :: OSI Approved :: Apache Software License
Classifier: Operating System :: OS Independent
Requires-Python: >=3.0
Requires-Dist: argparse (==1.4.0)
Requires-Dist: lxml (==4.5.0)
Requires-Dist: utm (==0.7.0)
